qcd_gym/__init__.py
qcd_gym/env.py
qcd_gym/wrappers/__init__.py
qcd_gym/wrappers/monitor.py
qcd_gym-0.2.0.dist-info/LICENSE
qcd_gym-0.2.0.dist-info/METADATA
qcd_gym-0.2.0.dist-info/WHEEL
qcd_gym-0.2.0.dist-info/entry_points.txt
qcd_gym-0.2.0.dist-info/top_level.txt
qcd_gym-0.2.0.dist-info/RECORD
