Metadata-Version: 2.1
Name: qcd-gym
Version: 0.2.0
Summary: Quantum Circuit Designer: A gymnasium-based set of environments for benchmarking reinforcement learning for quantum circuit design.
Home-page: https://github.com/philippaltmann/qcd
Author-email: philipp@hyphi.co
License: MIT
Keywords: benchmark reinforcement-learning quantum-computing gymnasium circuit-design
Requires-Python: >=3.8
License-File: LICENSE
Requires-Dist: gymnasium ==0.29
Requires-Dist: qiskit ==1.0.2
Provides-Extra: all
Requires-Dist: torch ==2.0.1 ; extra == 'all'
Requires-Dist: stable-baselines3 >=2.0.0 ; extra == 'all'
Requires-Dist: tqdm >=4.65.0 ; extra == 'all'
Requires-Dist: plotly >=5.0 ; extra == 'all'
Requires-Dist: tensorboard >=2.0 ; extra == 'all'
Provides-Extra: plot
Requires-Dist: plotly >=5.0 ; extra == 'plot'
Requires-Dist: tensorboard >=2.0 ; extra == 'plot'
Provides-Extra: tests
Requires-Dist: pytest ; extra == 'tests'
Requires-Dist: black ; extra == 'tests'
Provides-Extra: train
Requires-Dist: torch ==2.0.1 ; extra == 'train'
Requires-Dist: stable-baselines3 >=2.0.0 ; extra == 'train'
Requires-Dist: tqdm >=4.65.0 ; extra == 'train'
